django_nose/__init__.py
django_nose/fixture_tables.py
django_nose/plugin.py
django_nose/runner.py
django_nose/testcases.py
django_nose/tools.py
django_nose/utils.py
django_nose/management/__init__.py
django_nose/management/commands/__init__.py
django_nose/management/commands/test.py
django_nose-1.4.6.dist-info/DESCRIPTION.rst
django_nose-1.4.6.dist-info/METADATA
django_nose-1.4.6.dist-info/RECORD
django_nose-1.4.6.dist-info/WHEEL
django_nose-1.4.6.dist-info/metadata.json
django_nose-1.4.6.dist-info/top_level.txt
testapp/migrations/0001_initial.py
testapp/migrations/__init__.py
